cheche_pm/__init__.py
cheche_pm/cheche_pm.py
cheche_pm-0.1.13.dist-info/AUTHORS.rst
cheche_pm-0.1.13.dist-info/LICENSE
cheche_pm-0.1.13.dist-info/METADATA
cheche_pm-0.1.13.dist-info/WHEEL
cheche_pm-0.1.13.dist-info/top_level.txt
cheche_pm-0.1.13.dist-info/RECORD
