Metadata-Version: 2.1
Name: cheche-pm
Version: 0.1.13
Summary: A python package dedicated to project scheduling
Home-page: https://github.com/ceche1212/cheche_pm
Author: Luis Fernando Pérez Armas
Author-email: luisfernandopa1212@gmail.com
License: MIT license
Keywords: cheche_pm
Classifier: Development Status :: 2 - Pre-Alpha
Classifier: Intended Audience :: Developers
Classifier: License :: OSI Approved :: MIT License
Classifier: Natural Language :: English
Classifier: Programming Language :: Python :: 3
Classifier: Programming Language :: Python :: 3.6
Classifier: Programming Language :: Python :: 3.7
Classifier: Programming Language :: Python :: 3.8
Classifier: Programming Language :: Python :: 3.9
Classifier: Programming Language :: Python :: 3.10
Requires-Python: >=3.9
License-File: LICENSE
License-File: AUTHORS.rst
Requires-Dist: numpy
Requires-Dist: pandas
Requires-Dist: matplotlib
Requires-Dist: tqdm
Requires-Dist: networkx
Requires-Dist: pydot
Requires-Dist: plotly
Requires-Dist: scipy
Requires-Dist: openpyxl
